{
    "command": "list",
    "commandOptions": {
        "dotFile": "output/67220a54-7c01-40e5-aa06-7906a5e44760.dot",
        "title": "",
        "provider": [
            "aws"
        ],
        "all": true,
        "graph": true,
        "typesExclude": [
            "IamBinding",
            "IamPolicy",
            "ServiceAccount"
        ]
    },
    "programOptions": {
        "infra": "iac_aws.js",
        "json": "output/gc-list-67220a54-7c01-40e5-aa06-7906a5e44760.json"
    },
    "result": {
        "error": false,
        "results": [
            {
                "providerName": "aws",
                "kind": "livesPerType",
                "error": false,
                "results": [
                    {
                        "type": "NetworkAcl",
                        "group": "ec2",
                        "resources": [
                            {
                                "uri": "aws::ec2::NetworkAcl::acl-dd3a31a0",
                                "name": "acl-dd3a31a0",
                                "displayName": "acl-dd3a31a0",
                                "id": "acl-dd3a31a0",
                                "providerName": "aws",
                                "type": "NetworkAcl",
                                "group": "ec2",
                                "live": {
                                    "Associations": [
                                        {
                                            "NetworkAclAssociationId": "aclassoc-a550f6f7",
                                            "NetworkAclId": "acl-dd3a31a0",
                                            "SubnetId": "subnet-c113348c"
                                        },
                                        {
                                            "NetworkAclAssociationId": "aclassoc-a450f6f6",
                                            "NetworkAclId": "acl-dd3a31a0",
                                            "SubnetId": "subnet-4914802f"
                                        },
                                        {
                                            "NetworkAclAssociationId": "aclassoc-a850f6fa",
                                            "NetworkAclId": "acl-dd3a31a0",
                                            "SubnetId": "subnet-79c08e77"
                                        },
                                        {
                                            "NetworkAclAssociationId": "aclassoc-a950f6fb",
                                            "NetworkAclId": "acl-dd3a31a0",
                                            "SubnetId": "subnet-b1bb2990"
                                        },
                                        {
                                            "NetworkAclAssociationId": "aclassoc-aa50f6f8",
                                            "NetworkAclId": "acl-dd3a31a0",
                                            "SubnetId": "subnet-7e2fbe21"
                                        },
                                        {
                                            "NetworkAclAssociationId": "aclassoc-ab50f6f9",
                                            "NetworkAclId": "acl-dd3a31a0",
                                            "SubnetId": "subnet-5fe2396e"
                                        }
                                    ],
                                    "Entries": [
                                        {
                                            "CidrBlock": "0.0.0.0/0",
                                            "Egress": true,
                                            "Protocol": "-1",
                                            "RuleAction": "allow",
                                            "RuleNumber": 100
                                        },
                                        {
                                            "CidrBlock": "0.0.0.0/0",
                                            "Egress": true,
                                            "Protocol": "-1",
                                            "RuleAction": "deny",
                                            "RuleNumber": 32767
                                        },
                                        {
                                            "CidrBlock": "0.0.0.0/0",
                                            "Egress": false,
                                            "Protocol": "-1",
                                            "RuleAction": "allow",
                                            "RuleNumber": 100
                                        },
                                        {
                                            "CidrBlock": "0.0.0.0/0",
                                            "Egress": false,
                                            "Protocol": "-1",
                                            "RuleAction": "deny",
                                            "RuleNumber": 32767
                                        }
                                    ],
                                    "IsDefault": true,
                                    "NetworkAclId": "acl-dd3a31a0",
                                    "Tags": [],
                                    "VpcId": "vpc-904ceced",
                                    "OwnerId": "594073614517"
                                },
                                "cannotBeDeleted": false,
                                "isDefault": true,
                                "namespace": "",
                                "dependencies": [
                                    {
                                        "type": "Vpc",
                                        "ids": [
                                            "vpc-904ceced"
                                        ]
                                    },
                                    {
                                        "type": "Subnet",
                                        "ids": [
                                            "subnet-c113348c",
                                            "subnet-4914802f",
                                            "subnet-79c08e77",
                                            "subnet-b1bb2990",
                                            "subnet-7e2fbe21",
                                            "subnet-5fe2396e"
                                        ]
                                    }
                                ],
                                "managedByUs": false,
                                "show": true
                            }
                        ]
                    },
                    {
                        "type": "Domain",
                        "group": "route53Domain",
                        "resources": [
                            {
                                "uri": "aws::route53Domain::Domain::starhack.it",
                                "name": "starhack.it",
                                "displayName": "starhack.it",
                                "id": "starhack.it",
                                "providerName": "aws",
                                "type": "Domain",
                                "group": "route53Domain",
                                "live": {
                                    "DomainName": "starhack.it",
                                    "Nameservers": [
                                        {
                                            "Name": "ns-1752.awsdns-27.co.uk",
                                            "GlueIps": []
                                        },
                                        {
                                            "Name": "ns-1089.awsdns-08.org",
                                            "GlueIps": []
                                        },
                                        {
                                            "Name": "ns-36.awsdns-04.com",
                                            "GlueIps": []
                                        },
                                        {
                                            "Name": "ns-674.awsdns-20.net",
                                            "GlueIps": []
                                        }
                                    ],
                                    "AutoRenew": true,
                                    "AdminContact": {
                                        "FirstName": "Frederic",
                                        "LastName": "heem",
                                        "ContactType": "PERSON",
                                        "AddressLine1": "flat 7",
                                        "AddressLine2": "friern park",
                                        "City": "LONDON",
                                        "CountryCode": "GB",
                                        "ZipCode": "N12 9LA",
                                        "PhoneNumber": "+44.7479336201",
                                        "Email": "frederic.heem@gmail.com",
                                        "ExtraParams": [
                                            {
                                                "Name": "IT_PIN",
                                                "Value": "HMEFDR78H11Z110H"
                                            },
                                            {
                                                "Name": "IT_NATIONALITY",
                                                "Value": "FR"
                                            }
                                        ]
                                    },
                                    "RegistrantContact": {
                                        "FirstName": "Frederic",
                                        "LastName": "heem",
                                        "ContactType": "PERSON",
                                        "AddressLine1": "flat 7",
                                        "AddressLine2": "friern park",
                                        "City": "LONDON",
                                        "CountryCode": "GB",
                                        "ZipCode": "N12 9LA",
                                        "PhoneNumber": "+44.7479336201",
                                        "Email": "frederic.heem@gmail.com",
                                        "ExtraParams": [
                                            {
                                                "Name": "IT_PIN",
                                                "Value": "HMEFDR78H11Z110H"
                                            },
                                            {
                                                "Name": "IT_NATIONALITY",
                                                "Value": "FR"
                                            }
                                        ]
                                    },
                                    "TechContact": {
                                        "FirstName": "Frederic",
                                        "LastName": "heem",
                                        "ContactType": "PERSON",
                                        "AddressLine1": "flat 7",
                                        "AddressLine2": "friern park",
                                        "City": "LONDON",
                                        "CountryCode": "GB",
                                        "ZipCode": "N12 9LA",
                                        "PhoneNumber": "+44.7479336201",
                                        "Email": "frederic.heem@gmail.com",
                                        "ExtraParams": [
                                            {
                                                "Name": "IT_PIN",
                                                "Value": "HMEFDR78H11Z110H"
                                            },
                                            {
                                                "Name": "IT_NATIONALITY",
                                                "Value": "FR"
                                            }
                                        ]
                                    },
                                    "AdminPrivacy": true,
                                    "RegistrantPrivacy": true,
                                    "TechPrivacy": true,
                                    "RegistrarName": "GANDI SAS",
                                    "WhoIsServer": "whois.gandi.net",
                                    "RegistrarUrl": "http://www.gandi.net",
                                    "AbuseContactEmail": "abuse@support.gandi.net",
                                    "AbuseContactPhone": "+33.170377661",
                                    "CreationDate": "2015-10-13T13:43:17.000Z",
                                    "UpdatedDate": "2021-02-04T16:10:29.000Z",
                                    "ExpirationDate": "2022-01-10T22:59:59.000Z"
                                },
                                "cannotBeDeleted": true,
                                "isDefault": false,
                                "namespace": "",
                                "dependencies": [],
                                "managedByUs": false,
                                "show": true
                            }
                        ]
                    },
                    {
                        "type": "Role",
                        "group": "iam",
                        "resources": [
                            {
                                "uri": "aws::iam::Role::arn:aws:iam::594073614517:role/OrganizationAccountAccessRole",
                                "name": "OrganizationAccountAccessRole",
                                "displayName": "OrganizationAccountAccessRole",
                                "id": "arn:aws:iam::594073614517:role/OrganizationAccountAccessRole",
                                "providerName": "aws",
                                "type": "Role",
                                "group": "iam",
                                "live": {
                                    "Path": "/",
                                    "RoleName": "OrganizationAccountAccessRole",
                                    "RoleId": "AROAYUUML7C2STIJOIOEH",
                                    "Arn": "arn:aws:iam::594073614517:role/OrganizationAccountAccessRole",
                                    "CreateDate": "2021-02-02T17:43:34.000Z",
                                    "AssumeRolePolicyDocument": {
                                        "Version": "2012-10-17",
                                        "Statement": [
                                            {
                                                "Effect": "Allow",
                                                "Principal": {
                                                    "AWS": "arn:aws:iam::840541460064:root"
                                                },
                                                "Action": "sts:AssumeRole"
                                            }
                                        ]
                                    },
                                    "MaxSessionDuration": 3600,
                                    "Tags": [],
                                    "Policies": [
                                        "AdministratorAccess"
                                    ],
                                    "AttachedPolicies": [],
                                    "InstanceProfiles": []
                                },
                                "cannotBeDeleted": false,
                                "isDefault": false,
                                "namespace": "",
                                "dependencies": [
                                    {
                                        "type": "IamPolicy",
                                        "ids": []
                                    },
                                    {
                                        "type": "IamOpenIDConnectProvider",
                                        "ids": []
                                    }
                                ],
                                "managedByUs": false,
                                "show": true
                            },
                            {
                                "uri": "aws::iam::Role::arn:aws:iam::594073614517:role/role-cluster",
                                "name": "role-cluster",
                                "displayName": "role-cluster",
                                "id": "arn:aws:iam::594073614517:role/role-cluster",
                                "providerName": "aws",
                                "type": "Role",
                                "group": "iam",
                                "live": {
                                    "Path": "/",
                                    "RoleName": "role-cluster",
                                    "RoleId": "AROAYUUML7C22FVAL335R",
                                    "Arn": "arn:aws:iam::594073614517:role/role-cluster",
                                    "CreateDate": "2021-05-06T04:32:08.000Z",
                                    "AssumeRolePolicyDocument": {
                                        "Version": "2012-10-17",
                                        "Statement": [
                                            {
                                                "Effect": "Allow",
                                                "Principal": {
                                                    "Service": "eks.amazonaws.com"
                                                },
                                                "Action": "sts:AssumeRole"
                                            }
                                        ]
                                    },
                                    "MaxSessionDuration": 3600,
                                    "Tags": [
                                        {
                                            "Key": "Name",
                                            "Value": "role-cluster"
                                        },
                                        {
                                            "Key": "ManagedBy",
                                            "Value": "GruCloud"
                                        },
                                        {
                                            "Key": "CreatedByProvider",
                                            "Value": "aws"
                                        },
                                        {
                                            "Key": "stage",
                                            "Value": "dev"
                                        },
                                        {
                                            "Key": "projectName",
                                            "Value": "starhackit"
                                        },
                                        {
                                            "Key": "namespace",
                                            "Value": "EKS"
                                        }
                                    ],
                                    "AttachedPolicies": [
                                        {
                                            "PolicyName": "AmazonEKSClusterPolicy",
                                            "PolicyArn": "arn:aws:iam::aws:policy/AmazonEKSClusterPolicy"
                                        },
                                        {
                                            "PolicyName": "AmazonEKSVPCResourceController",
                                            "PolicyArn": "arn:aws:iam::aws:policy/AmazonEKSVPCResourceController"
                                        }
                                    ],
                                    "InstanceProfiles": [],
                                    "Policies": []
                                },
                                "cannotBeDeleted": false,
                                "isDefault": false,
                                "namespace": "EKS",
                                "dependencies": [
                                    {
                                        "type": "IamPolicy",
                                        "ids": [
                                            "arn:aws:iam::aws:policy/AmazonEKSClusterPolicy",
                                            "arn:aws:iam::aws:policy/AmazonEKSVPCResourceController"
                                        ]
                                    },
                                    {
                                        "type": "IamOpenIDConnectProvider",
                                        "ids": []
                                    }
                                ],
                                "managedByUs": false,
                                "show": true
                            },
                            {
                                "uri": "aws::iam::Role::arn:aws:iam::594073614517:role/role-node-group",
                                "name": "role-node-group",
                                "displayName": "role-node-group",
                                "id": "arn:aws:iam::594073614517:role/role-node-group",
                                "providerName": "aws",
                                "type": "Role",
                                "group": "iam",
                                "live": {
                                    "Path": "/",
                                    "RoleName": "role-node-group",
                                    "RoleId": "AROAYUUML7C24J7UEVWED",
                                    "Arn": "arn:aws:iam::594073614517:role/role-node-group",
                                    "CreateDate": "2021-05-06T04:32:08.000Z",
                                    "AssumeRolePolicyDocument": {
                                        "Version": "2012-10-17",
                                        "Statement": [
                                            {
                                                "Effect": "Allow",
                                                "Principal": {
                                                    "Service": "ec2.amazonaws.com"
                                                },
                                                "Action": "sts:AssumeRole"
                                            }
                                        ]
                                    },
                                    "MaxSessionDuration": 3600,
                                    "Tags": [
                                        {
                                            "Key": "Name",
                                            "Value": "role-node-group"
                                        },
                                        {
                                            "Key": "ManagedBy",
                                            "Value": "GruCloud"
                                        },
                                        {
                                            "Key": "CreatedByProvider",
                                            "Value": "aws"
                                        },
                                        {
                                            "Key": "stage",
                                            "Value": "dev"
                                        },
                                        {
                                            "Key": "projectName",
                                            "Value": "starhackit"
                                        },
                                        {
                                            "Key": "namespace",
                                            "Value": "EKS"
                                        }
                                    ],
                                    "Policies": [],
                                    "AttachedPolicies": [
                                        {
                                            "PolicyName": "AmazonEKSWorkerNodePolicy",
                                            "PolicyArn": "arn:aws:iam::aws:policy/AmazonEKSWorkerNodePolicy"
                                        },
                                        {
                                            "PolicyName": "AmazonEC2ContainerRegistryReadOnly",
                                            "PolicyArn": "arn:aws:iam::aws:policy/AmazonEC2ContainerRegistryReadOnly"
                                        },
                                        {
                                            "PolicyName": "AmazonEKS_CNI_Policy",
                                            "PolicyArn": "arn:aws:iam::aws:policy/AmazonEKS_CNI_Policy"
                                        }
                                    ],
                                    "InstanceProfiles": []
                                },
                                "cannotBeDeleted": false,
                                "isDefault": false,
                                "namespace": "EKS",
                                "dependencies": [
                                    {
                                        "type": "IamPolicy",
                                        "ids": [
                                            "arn:aws:iam::aws:policy/AmazonEKSWorkerNodePolicy",
                                            "arn:aws:iam::aws:policy/AmazonEC2ContainerRegistryReadOnly",
                                            "arn:aws:iam::aws:policy/AmazonEKS_CNI_Policy"
                                        ]
                                    },
                                    {
                                        "type": "IamOpenIDConnectProvider",
                                        "ids": []
                                    }
                                ],
                                "managedByUs": false,
                                "show": true
                            }
                        ]
                    },
                    {
                        "type": "HostedZone",
                        "group": "route53",
                        "resources": [
                            {
                                "uri": "aws::route53::HostedZone::/hostedzone/Z09429703J0B6XPB98IZ9",
                                "name": "starhack.it.",
                                "displayName": "starhack.it.",
                                "id": "/hostedzone/Z09429703J0B6XPB98IZ9",
                                "providerName": "aws",
                                "type": "HostedZone",
                                "group": "route53",
                                "live": {
                                    "Id": "/hostedzone/Z09429703J0B6XPB98IZ9",
                                    "Name": "starhack.it.",
                                    "CallerReference": "grucloud-Fri Apr 30 2021 00:26:41 GMT-0500 (Colombia Standard Time)",
                                    "Config": {
                                        "PrivateZone": false
                                    },
                                    "ResourceRecordSetCount": 3,
                                    "RecordSet": [
                                        {
                                            "Name": "starhack.it.",
                                            "Type": "A",
                                            "TTL": 60,
                                            "ResourceRecords": [
                                                {
                                                    "Value": "18.130.120.30"
                                                }
                                            ]
                                        },
                                        {
                                            "Name": "starhack.it.",
                                            "Type": "NS",
                                            "TTL": 172800,
                                            "ResourceRecords": [
                                                {
                                                    "Value": "ns-1752.awsdns-27.co.uk."
                                                },
                                                {
                                                    "Value": "ns-1089.awsdns-08.org."
                                                },
                                                {
                                                    "Value": "ns-36.awsdns-04.com."
                                                },
                                                {
                                                    "Value": "ns-674.awsdns-20.net."
                                                }
                                            ]
                                        },
                                        {
                                            "Name": "starhack.it.",
                                            "Type": "SOA",
                                            "TTL": 900,
                                            "ResourceRecords": [
                                                {
                                                    "Value": "ns-1752.awsdns-27.co.uk. awsdns-hostmaster.amazon.com. 1 7200 900 1209600 86400"
                                                }
                                            ]
                                        }
                                    ],
                                    "Tags": [
                                        {
                                            "Key": "DelegationSetId",
                                            "Value": "N07547383GD2HQNOQVK2N"
                                        },
                                        {
                                            "Key": "ManagedBy",
                                            "Value": "GruCloud"
                                        },
                                        {
                                            "Key": "stage",
                                            "Value": "dev"
                                        },
                                        {
                                            "Key": "starhack.it.",
                                            "Value": "starhack.it.-ipv4"
                                        },
                                        {
                                            "Key": "CreatedByProvider",
                                            "Value": "aws"
                                        },
                                        {
                                            "Key": "projectName",
                                            "Value": "grucloud-aws-starhackit"
                                        },
                                        {
                                            "Key": "Name",
                                            "Value": "starhack.it."
                                        }
                                    ]
                                },
                                "cannotBeDeleted": false,
                                "isDefault": false,
                                "namespace": "",
                                "dependencies": [
                                    {
                                        "type": "HostedZone",
                                        "ids": []
                                    }
                                ],
                                "managedByUs": false,
                                "show": true
                            }
                        ]
                    },
                    {
                        "type": "Vpc",
                        "group": "ec2",
                        "resources": [
                            {
                                "uri": "aws::ec2::Vpc::vpc-904ceced",
                                "name": "default",
                                "displayName": "default",
                                "id": "vpc-904ceced",
                                "providerName": "aws",
                                "type": "Vpc",
                                "group": "ec2",
                                "live": {
                                    "CidrBlock": "172.31.0.0/16",
                                    "DhcpOptionsId": "dopt-814e03fb",
                                    "State": "available",
                                    "VpcId": "vpc-904ceced",
                                    "OwnerId": "594073614517",
                                    "InstanceTenancy": "default",
                                    "Ipv6CidrBlockAssociationSet": [],
                                    "CidrBlockAssociationSet": [
                                        {
                                            "AssociationId": "vpc-cidr-assoc-cf02bfa0",
                                            "CidrBlock": "172.31.0.0/16",
                                            "CidrBlockState": {
                                                "State": "associated"
                                            }
                                        }
                                    ],
                                    "IsDefault": true,
                                    "Tags": [],
                                    "DnsSupport": true,
                                    "DnsHostnames": true
                                },
                                "cannotBeDeleted": true,
                                "isDefault": true,
                                "namespace": "",
                                "dependencies": [],
                                "managedByUs": false,
                                "show": true
                            }
                        ]
                    },
                    {
                        "type": "InternetGateway",
                        "group": "ec2",
                        "resources": [
                            {
                                "uri": "aws::ec2::InternetGateway::igw-7bdccb00",
                                "name": "igw-7bdccb00",
                                "displayName": "igw-7bdccb00",
                                "id": "igw-7bdccb00",
                                "providerName": "aws",
                                "type": "InternetGateway",
                                "group": "ec2",
                                "live": {
                                    "Attachments": [
                                        {
                                            "State": "available",
                                            "VpcId": "vpc-904ceced"
                                        }
                                    ],
                                    "InternetGatewayId": "igw-7bdccb00",
                                    "OwnerId": "594073614517",
                                    "Tags": []
                                },
                                "cannotBeDeleted": true,
                                "isDefault": true,
                                "namespace": "",
                                "dependencies": [
                                    {
                                        "type": "Vpc",
                                        "ids": [
                                            "vpc-904ceced"
                                        ]
                                    }
                                ],
                                "managedByUs": false,
                                "show": true
                            }
                        ]
                    },
                    {
                        "type": "Subnet",
                        "group": "ec2",
                        "resources": [
                            {
                                "uri": "aws::ec2::Subnet::subnet-c113348c",
                                "name": "default",
                                "displayName": "default",
                                "id": "subnet-c113348c",
                                "providerName": "aws",
                                "type": "Subnet",
                                "group": "ec2",
                                "live": {
                                    "AvailabilityZone": "us-east-1d",
                                    "AvailabilityZoneId": "use1-az4",
                                    "AvailableIpAddressCount": 4091,
                                    "CidrBlock": "172.31.16.0/20",
                                    "DefaultForAz": true,
                                    "MapPublicIpOnLaunch": true,
                                    "MapCustomerOwnedIpOnLaunch": false,
                                    "State": "available",
                                    "SubnetId": "subnet-c113348c",
                                    "VpcId": "vpc-904ceced",
                                    "OwnerId": "594073614517",
                                    "AssignIpv6AddressOnCreation": false,
                                    "Ipv6CidrBlockAssociationSet": [],
                                    "Tags": [],
                                    "SubnetArn": "arn:aws:ec2:us-east-1:594073614517:subnet/subnet-c113348c"
                                },
                                "cannotBeDeleted": true,
                                "isDefault": true,
                                "namespace": "",
                                "dependencies": [
                                    {
                                        "type": "Vpc",
                                        "ids": [
                                            "vpc-904ceced"
                                        ]
                                    }
                                ],
                                "managedByUs": false,
                                "show": true
                            },
                            {
                                "uri": "aws::ec2::Subnet::subnet-5fe2396e",
                                "name": "default",
                                "displayName": "default",
                                "id": "subnet-5fe2396e",
                                "providerName": "aws",
                                "type": "Subnet",
                                "group": "ec2",
                                "live": {
                                    "AvailabilityZone": "us-east-1e",
                                    "AvailabilityZoneId": "use1-az3",
                                    "AvailableIpAddressCount": 4091,
                                    "CidrBlock": "172.31.48.0/20",
                                    "DefaultForAz": true,
                                    "MapPublicIpOnLaunch": true,
                                    "MapCustomerOwnedIpOnLaunch": false,
                                    "State": "available",
                                    "SubnetId": "subnet-5fe2396e",
                                    "VpcId": "vpc-904ceced",
                                    "OwnerId": "594073614517",
                                    "AssignIpv6AddressOnCreation": false,
                                    "Ipv6CidrBlockAssociationSet": [],
                                    "Tags": [],
                                    "SubnetArn": "arn:aws:ec2:us-east-1:594073614517:subnet/subnet-5fe2396e"
                                },
                                "cannotBeDeleted": true,
                                "isDefault": true,
                                "namespace": "",
                                "dependencies": [
                                    {
                                        "type": "Vpc",
                                        "ids": [
                                            "vpc-904ceced"
                                        ]
                                    }
                                ],
                                "managedByUs": false,
                                "show": true
                            },
                            {
                                "uri": "aws::ec2::Subnet::subnet-79c08e77",
                                "name": "default",
                                "displayName": "default",
                                "id": "subnet-79c08e77",
                                "providerName": "aws",
                                "type": "Subnet",
                                "group": "ec2",
                                "live": {
                                    "AvailabilityZone": "us-east-1f",
                                    "AvailabilityZoneId": "use1-az5",
                                    "AvailableIpAddressCount": 4091,
                                    "CidrBlock": "172.31.64.0/20",
                                    "DefaultForAz": true,
                                    "MapPublicIpOnLaunch": true,
                                    "MapCustomerOwnedIpOnLaunch": false,
                                    "State": "available",
                                    "SubnetId": "subnet-79c08e77",
                                    "VpcId": "vpc-904ceced",
                                    "OwnerId": "594073614517",
                                    "AssignIpv6AddressOnCreation": false,
                                    "Ipv6CidrBlockAssociationSet": [],
                                    "Tags": [],
                                    "SubnetArn": "arn:aws:ec2:us-east-1:594073614517:subnet/subnet-79c08e77"
                                },
                                "cannotBeDeleted": true,
                                "isDefault": true,
                                "namespace": "",
                                "dependencies": [
                                    {
                                        "type": "Vpc",
                                        "ids": [
                                            "vpc-904ceced"
                                        ]
                                    }
                                ],
                                "managedByUs": false,
                                "show": true
                            },
                            {
                                "uri": "aws::ec2::Subnet::subnet-7e2fbe21",
                                "name": "default",
                                "displayName": "default",
                                "id": "subnet-7e2fbe21",
                                "providerName": "aws",
                                "type": "Subnet",
                                "group": "ec2",
                                "live": {
                                    "AvailabilityZone": "us-east-1a",
                                    "AvailabilityZoneId": "use1-az6",
                                    "AvailableIpAddressCount": 4091,
                                    "CidrBlock": "172.31.32.0/20",
                                    "DefaultForAz": true,
                                    "MapPublicIpOnLaunch": true,
                                    "MapCustomerOwnedIpOnLaunch": false,
                                    "State": "available",
                                    "SubnetId": "subnet-7e2fbe21",
                                    "VpcId": "vpc-904ceced",
                                    "OwnerId": "594073614517",
                                    "AssignIpv6AddressOnCreation": false,
                                    "Ipv6CidrBlockAssociationSet": [],
                                    "Tags": [],
                                    "SubnetArn": "arn:aws:ec2:us-east-1:594073614517:subnet/subnet-7e2fbe21"
                                },
                                "cannotBeDeleted": true,
                                "isDefault": true,
                                "namespace": "",
                                "dependencies": [
                                    {
                                        "type": "Vpc",
                                        "ids": [
                                            "vpc-904ceced"
                                        ]
                                    }
                                ],
                                "managedByUs": false,
                                "show": true
                            },
                            {
                                "uri": "aws::ec2::Subnet::subnet-4914802f",
                                "name": "default",
                                "displayName": "default",
                                "id": "subnet-4914802f",
                                "providerName": "aws",
                                "type": "Subnet",
                                "group": "ec2",
                                "live": {
                                    "AvailabilityZone": "us-east-1b",
                                    "AvailabilityZoneId": "use1-az1",
                                    "AvailableIpAddressCount": 4091,
                                    "CidrBlock": "172.31.0.0/20",
                                    "DefaultForAz": true,
                                    "MapPublicIpOnLaunch": true,
                                    "MapCustomerOwnedIpOnLaunch": false,
                                    "State": "available",
                                    "SubnetId": "subnet-4914802f",
                                    "VpcId": "vpc-904ceced",
                                    "OwnerId": "594073614517",
                                    "AssignIpv6AddressOnCreation": false,
                                    "Ipv6CidrBlockAssociationSet": [],
                                    "Tags": [],
                                    "SubnetArn": "arn:aws:ec2:us-east-1:594073614517:subnet/subnet-4914802f"
                                },
                                "cannotBeDeleted": true,
                                "isDefault": true,
                                "namespace": "",
                                "dependencies": [
                                    {
                                        "type": "Vpc",
                                        "ids": [
                                            "vpc-904ceced"
                                        ]
                                    }
                                ],
                                "managedByUs": false,
                                "show": true
                            },
                            {
                                "uri": "aws::ec2::Subnet::subnet-b1bb2990",
                                "name": "default",
                                "displayName": "default",
                                "id": "subnet-b1bb2990",
                                "providerName": "aws",
                                "type": "Subnet",
                                "group": "ec2",
                                "live": {
                                    "AvailabilityZone": "us-east-1c",
                                    "AvailabilityZoneId": "use1-az2",
                                    "AvailableIpAddressCount": 4091,
                                    "CidrBlock": "172.31.80.0/20",
                                    "DefaultForAz": true,
                                    "MapPublicIpOnLaunch": true,
                                    "MapCustomerOwnedIpOnLaunch": false,
                                    "State": "available",
                                    "SubnetId": "subnet-b1bb2990",
                                    "VpcId": "vpc-904ceced",
                                    "OwnerId": "594073614517",
                                    "AssignIpv6AddressOnCreation": false,
                                    "Ipv6CidrBlockAssociationSet": [],
                                    "Tags": [],
                                    "SubnetArn": "arn:aws:ec2:us-east-1:594073614517:subnet/subnet-b1bb2990"
                                },
                                "cannotBeDeleted": true,
                                "isDefault": true,
                                "namespace": "",
                                "dependencies": [
                                    {
                                        "type": "Vpc",
                                        "ids": [
                                            "vpc-904ceced"
                                        ]
                                    }
                                ],
                                "managedByUs": false,
                                "show": true
                            }
                        ]
                    },
                    {
                        "type": "SecurityGroup",
                        "group": "ec2",
                        "resources": [
                            {
                                "uri": "aws::ec2::SecurityGroup::sg-15c54c1e",
                                "name": "default",
                                "displayName": "default",
                                "id": "sg-15c54c1e",
                                "providerName": "aws",
                                "type": "SecurityGroup",
                                "group": "ec2",
                                "live": {
                                    "Description": "default VPC security group",
                                    "GroupName": "default",
                                    "IpPermissions": [
                                        {
                                            "IpProtocol": "-1",
                                            "IpRanges": [],
                                            "Ipv6Ranges": [],
                                            "PrefixListIds": [],
                                            "UserIdGroupPairs": [
                                                {
                                                    "GroupId": "sg-15c54c1e",
                                                    "UserId": "594073614517"
                                                }
                                            ]
                                        }
                                    ],
                                    "OwnerId": "594073614517",
                                    "GroupId": "sg-15c54c1e",
                                    "IpPermissionsEgress": [
                                        {
                                            "IpProtocol": "-1",
                                            "IpRanges": [
                                                {
                                                    "CidrIp": "0.0.0.0/0"
                                                }
                                            ],
                                            "Ipv6Ranges": [],
                                            "PrefixListIds": [],
                                            "UserIdGroupPairs": []
                                        }
                                    ],
                                    "Tags": [],
                                    "VpcId": "vpc-904ceced"
                                },
                                "cannotBeDeleted": true,
                                "isDefault": true,
                                "dependencies": [
                                    {
                                        "type": "Vpc",
                                        "ids": [
                                            "vpc-904ceced"
                                        ]
                                    },
                                    {
                                        "type": "SecurityGroup",
                                        "ids": [
                                            "sg-15c54c1e"
                                        ]
                                    }
                                ],
                                "managedByUs": false,
                                "show": true
                            }
                        ]
                    },
                    {
                        "type": "RouteTable",
                        "group": "ec2",
                        "resources": [
                            {
                                "uri": "aws::ec2::RouteTable::rtb-461d3238",
                                "name": "rtb-461d3238",
                                "displayName": "rtb-461d3238",
                                "id": "rtb-461d3238",
                                "providerName": "aws",
                                "type": "RouteTable",
                                "group": "ec2",
                                "live": {
                                    "Associations": [
                                        {
                                            "Main": true,
                                            "RouteTableAssociationId": "rtbassoc-b5a43bc4",
                                            "RouteTableId": "rtb-461d3238",
                                            "AssociationState": {
                                                "State": "associated"
                                            }
                                        }
                                    ],
                                    "PropagatingVgws": [],
                                    "RouteTableId": "rtb-461d3238",
                                    "Routes": [
                                        {
                                            "DestinationCidrBlock": "172.31.0.0/16",
                                            "GatewayId": "local",
                                            "Origin": "CreateRouteTable",
                                            "State": "active"
                                        },
                                        {
                                            "DestinationCidrBlock": "0.0.0.0/0",
                                            "GatewayId": "igw-7bdccb00",
                                            "Origin": "CreateRoute",
                                            "State": "active"
                                        }
                                    ],
                                    "Tags": [],
                                    "VpcId": "vpc-904ceced",
                                    "OwnerId": "594073614517"
                                },
                                "cannotBeDeleted": true,
                                "isDefault": true,
                                "namespace": "",
                                "dependencies": [
                                    {
                                        "type": "Vpc",
                                        "ids": [
                                            "vpc-904ceced"
                                        ]
                                    },
                                    {
                                        "type": "InternetGateway",
                                        "ids": [
                                            "igw-7bdccb00"
                                        ]
                                    }
                                ],
                                "managedByUs": false,
                                "show": true
                            }
                        ]
                    }
                ]
            }
        ],
        "kind": "livesPerProvider"
    }
}